[
  {
    "externalTeamName": "Huracan",
    "points": 35,
    "position": 1,
    "gamesPlayed": 10,
    "gamesWon": 7,
    "gamesDrawn": 0,
    "gamesLost": 3,
    "goalsFor": 22,
    "goalsAgainst": 12,
    "teamId": 1,
    "id": 10,
    "createdAt": "2025-03-31T19:27:36.108Z",
    "updatedAt": "2025-03-31T19:27:36.108Z"
  },
  {
    "externalTeamName": "Naviera",
    "points": 22,
    "position": 2,
    "gamesPlayed": 10,
    "gamesWon": 6,
    "gamesDrawn": 0,
    "gamesLost": 4,
    "goalsFor": 20,
    "goalsAgainst": 15,
    "teamId": 1,
    "id": 11,
    "createdAt": "2025-03-31T19:27:36.108Z",
    "updatedAt": "2025-03-31T19:27:36.108Z"
  },
  {
    "externalTeamName": "Pomares",
    "points": 16,
    "position": 3,
    "gamesPlayed": 10,
    "gamesWon": 5,
    "gamesDrawn": 0,
    "gamesLost": 5,
    "goalsFor": 17,
    "goalsAgainst": 18,
    "teamId": 1,
    "id": 12,
    "createdAt": "2025-03-31T19:27:36.108Z",
    "updatedAt": "2025-03-31T19:27:36.108Z"
  }
]